skill_add/__init__.py
skill_add-0.3.0.dist-info/METADATA
skill_add-0.3.0.dist-info/WHEEL
skill_add-0.3.0.dist-info/entry_points.txt
skill_add-0.3.0.dist-info/RECORD
