Metadata-Version: 2.4
Name: skill-add
Version: 0.3.0
Summary: Add Claude Code skills from GitHub to your project
License-Expression: MIT
Requires-Python: >=3.10
Requires-Dist: agent-resources>=0.1.0
